aresponses/__init__.py
aresponses/errors.py
aresponses/main.py
aresponses/utils.py
aresponses-3.0.0.dist-info/LICENSE
aresponses-3.0.0.dist-info/METADATA
aresponses-3.0.0.dist-info/WHEEL
aresponses-3.0.0.dist-info/entry_points.txt
aresponses-3.0.0.dist-info/top_level.txt
aresponses-3.0.0.dist-info/RECORD
