Metadata-Version: 2.1
Name: aresponses
Version: 3.0.0
Summary: Asyncio response mocking. Similar to the responses library used for 'requests'
Home-page: https://github.com/aresponses/aresponses
Author: Bryce Drennan
Author-email: aresponses@brycedrennan.com   
License: UNKNOWN
Download-URL: https://github.com/aresponses/aresponses/tarball/3.0.0
Keywords: asyncio,testing,responses
Platform: UNKNOWN
Classifier: Programming Language :: Python :: 3.7
Classifier: Programming Language :: Python :: 3.8
Classifier: Programming Language :: Python :: 3.9
Classifier: Programming Language :: Python :: 3.10
Classifier: Programming Language :: Python :: 3.11
Classifier: Programming Language :: Python :: 3.12
Classifier: License :: OSI Approved :: MIT License
Requires-Python: >=3.7
License-File: LICENSE
